<?xml version="1.0" encoding="UTF-8"?>
<odoo>
	<record id="muk_dms_directory_tree" model="ir.ui.view">
		<field name="name">muk_dms_directory.tree</field>
		<field name="model">muk_dms.directory</field>
		<field name="arch" type="xml">
			<tree string="Directories">
				<field name="name" />
				<field name="path_text" />
				<field name="root" />
			</tree>
		</field>
	</record>
	<record id="muk_dms_directory_form" model="ir.ui.view">
		<field name="name">muk_dms_directory.form</field>
		<field name="model">muk_dms.directory</field>
		<field name="arch" type="xml">
			<form string="Directory">
				<sheet>
					<label for="name" class="oe_edit_only" />
					<h1>
						<field name="name" />
					</h1>
					<separator string="Information" />
					<group>
						<field name="path_object" widget="dms_path" options="{'last_seperator':True}"/>
					</group>
					<group>
						<group>
							<field name="root" />
						</group>
						<group>
							<field name="parent_id" />
							<field name="is_root_directory" />
						</group>
					</group>
					<group>
						<group>
							<field name="count_files" />
						</group>
						<group>
							<field name="count_dirctories" />
						</group>
					</group>
					<notebook>
						<page string="Files">
							<field name="files">
								<tree string="Files">
									<field name="name" />
									<field name="file_size" />
									<field name="write_date" />
								</tree>
							</field>
						</page>
						<page string="Subdirectories">
							<field name="child_id">
								<tree string="Subdirectories">
									<field name="name" />
									<field name="path_text" />
									<field name="root" />
								</tree>
							</field>
						</page>
						<page string="Meta Information" groups="base.group_no_one">
							<group>
								<field name="id" />
							</group>
							<group>
								<group>
									<field name="create_date" readonly="1" />
									<field name="create_uid" readonly="1" />
								</group>
								<group>
									<field name="write_date" readonly="1" />
									<field name="write_uid" readonly="1" />
								</group>
							</group>
						</page>
						<page string="Access Information">
							<group>
								<group>
									<field name="perm_create" readonly="1" />
									<field name="perm_read" readonly="1" />
								</group>
								<group>
									<field name="perm_write" readonly="1" />
									<field name="perm_unlink" readonly="1" />
								</group>
							</group>
						</page>
					</notebook>
				</sheet>
				<div class="oe_chatter">
					<field name="message_follower_ids" widget="mail_followers" />
					<field name="message_ids" widget="mail_thread" />
				</div>
			</form>
		</field>
	</record>
	<record id="action_muk_dms_directory" model="ir.actions.act_window">
		<field name="name">Directories</field>
		<field name="res_model">muk_dms.directory</field>
		<field name="view_mode">tree,form</field>
	</record>
	<menuitem id="muk_muk_dms_directory_list" name="Directories"
		parent="cat_menu_muk_dms_models" action="action_muk_dms_directory" />
</odoo>
