<odoo>
	<record model="muk_dms.directory" id="database_directory0">
		<field name="name">Root_Directory</field>
	</record>
	<record model="muk_dms.directory" id="database_directory1">
		<field name="name">Documents</field>
		<field name="parent_id" ref="database_directory0"></field>
	</record>
	<record model="muk_dms.directory" id="database_directory2">
		<field name="name">PDF</field>
		<field name="parent_id" ref="database_directory1"></field>
	</record>
	<record model="muk_dms.directory" id="database_directory3">
		<field name="name">Images</field>
		<field name="parent_id" ref="database_directory0"></field>
	</record>
	<record model="muk_dms.directory" id="database_directory4">
		<field name="name">JPG</field>
		<field name="parent_id" ref="database_directory3"></field>
	</record>
	<record model="muk_dms.directory" id="database_directory5">
		<field name="name">PNG</field>
		<field name="parent_id" ref="database_directory3"></field>
	</record>
</odoo>